vairflow/__init__.py
vairflow-0.0.0.dist-info/METADATA
vairflow-0.0.0.dist-info/WHEEL
vairflow-0.0.0.dist-info/top_level.txt
vairflow-0.0.0.dist-info/RECORD
