Metadata-Version: 2.1
Name: vairflow
Version: 0.0.0
Summary: Coming soon
Author-email: Vairflow <dev@vairflow.com>
